nameunity/__init__.py
nameunity/__main__.py
nameunity/main.py
nameunity/lib/__init__.py
nameunity/lib/copy_file.py
nameunity/lib/formatters.py
nameunity/lib/image_date.py
nameunity-0.2.4.dist-info/LICENSE
nameunity-0.2.4.dist-info/METADATA
nameunity-0.2.4.dist-info/WHEEL
nameunity-0.2.4.dist-info/entry_points.txt
nameunity-0.2.4.dist-info/top_level.txt
nameunity-0.2.4.dist-info/RECORD
