Metadata-Version: 2.1
Name: nameunity
Version: 0.2.4
Summary: A simple tool to help you unity file names.
Home-page: https://github.com/lucasd11/nameunity
Author: LucasD11
Author-email: yuanzhendai@gmail.com
License: UNKNOWN
Platform: UNKNOWN
Classifier: Programming Language :: Python :: 3
Classifier: License :: OSI Approved :: MIT License
Classifier: Operating System :: OS Independent
Requires-Python: >=3.6
